README.rst
setup.py
cf_rating/__init__.py
codeforces_rating.egg-info/PKG-INFO
codeforces_rating.egg-info/SOURCES.txt
codeforces_rating.egg-info/dependency_links.txt
codeforces_rating.egg-info/top_level.txt