Metadata-Version: 1.2
Name: codeforces-rating
Version: 1.5.1
Summary: Codeforces Rating system implementation in python
Home-page: https://github.com/Officeyutong/codeforces-rating
Author: officeyutong
Author-email: officeyutong@163.com
Maintainer: officeyutong
Maintainer-email: officeyutong@163.com
License: MIT License
Platform: all
